hydroclassification/__init__.py
hydroclassification/test.py
hydroclassification/neuralnetworks/__init__.py
hydroclassification/neuralnetworks/dinet.py
hygeoclas/__init__.py
hygeoclas/test.py
hygeoclas/fonts/__init__.py
hygeoclas/fonts/cambria.py
hygeoclas/models/__init__.py
hygeoclas/models/annhcmod.py
hygeoclas/neuralnetworks/__init__.py
hygeoclas/neuralnetworks/dinet.py
hygeoclas/neuralnetworks/resnet1d.py
hygeoclas/neuralnetworks/squeezenet1d.py
hygeoclas/utils/__init__.py
hygeoclas/utils/changeover.py
hygeoclas/utils/crawl.py
hygeoclas/utils/dynamic.py
hygeoclas/utils/graphic.py
hygeoclas/utils/methods.py
hygeoclas/utils/numeric.py
hygeoclas/utils/support.py
package/__init__.py
package/test.py
hygeoclas-0.5.1.dist-info/LICENSE
hygeoclas-0.5.1.dist-info/METADATA
hygeoclas-0.5.1.dist-info/WHEEL
hygeoclas-0.5.1.dist-info/top_level.txt
hygeoclas-0.5.1.dist-info/RECORD
